{
  "handlers": [
    {
      "class": "pl.tomaszmichalak.example.web.common.CommonMessageConfigurableHandlerFactory",
      "route": {
        "method": "GET",
        "pathRegex": "/all*"
      },
      "config": {
        "commonMessage": "All common message!"
      }
    },
    {
      "class": "pl.tomaszmichalak.example.web.custom.CustomMessageConfigurableHandlerFactory",
      "route": {
        "method": "GET",
        "pathRegex": "/all*"
      },
      "config": {
        "customMessage": "All custom message!"
      }
    },
    {
      "class": "pl.tomaszmichalak.example.web.common.CommonMessageConfigurableHandlerFactory",
      "route": {
        "method": "GET",
        "path": "/common"
      },
      "config": {
        "commonMessage": "Common message!"
      }
    },
    {
      "class": "pl.tomaszmichalak.example.web.custom.CustomMessageConfigurableHandlerFactory",
      "route": {
        "method": "GET",
        "path": "/custom"
      },
      "config": {
        "customMessage": "Custom message!"
      }
    }
  ]
}